[
  {
    "title": "Selektion Name",
    "solution": "nat\u00fcrlich, idR gerichtet",
    "guid": "d4f88503037c1f94e2877c9fbb4d45f2"
  },
  {
    "title": "Selektion",
    "solution": "ver\u00e4ndert Genfrequenz die f\u00fcr Ph\u00e4notypen verantwortlich ist",
    "guid": "e4f4fb87c2040c2e875ae1293e32d825"
  },
  {
    "title": "Selektion Funktionsweise",
    "solution": "der reproduktive Fitness nach fortpflanzen",
    "guid": "823805396fe6da243dd039787101d288"
  },
  {
    "title": "Selektion Arten",
    "solution": "gerichtet, stabilisierend, aufspaltend",
    "guid": "2bba5ed1b2873db8b2dfec2d3720a987"
  },
  {
    "title": "Selektion gerichtet",
    "solution": "in eine Richtung",
    "guid": "dc637bbc8ba8ba1eaefaaed741e836a6"
  },
  {
    "title": "Selektion stabilisierend",
    "solution": "spezifischer",
    "guid": "245e10ebd55b99f58df8543ddcd18cb8"
  },
  {
    "title": "Selektion spaltend",
    "solution": "auf beide Seiten, nicht Mitte",
    "guid": "e103c1beb0b3bec8d2d2c854768a50e2"
  }
]